{
  "globals": {
    "Address": true,
    "AreaSeriesPartialOptions": true,
    "AssetRegistryAddress": true,
    "AuraBalAddress": true,
    "AuraHandlerAddress": true,
    "AuraHandlerAddressV1": true,
    "BalAddress": true,
    "BbUsdHandlerAddress": true,
    "BbUsdHandlerAddressV2": true,
    "CandlestickData": true,
    "CandlestickSeriesPartialOptions": true,
    "ColorType": true,
    "Component": true,
    "ComponentPublicInstance": true,
    "ComputedRef": true,
    "Config": true,
    "CrosshairMode": true,
    "CrvAddress": true,
    "CurveVotingAddress": true,
    "CvxAddress": true,
    "CvxCrvAddress": true,
    "CvxCrvFactoryAddress": true,
    "CvxCrvFactoryAddressV1": true,
    "CvxCrvUtilities": true,
    "CvxFxsAddress": true,
    "CvxFxsFactoryAddress": true,
    "CvxFxsFactoryERC20Address": true,
    "CvxFxsStaking": true,
    "CvxPrismaAddress": true,
    "CvxPrismaFactoryAddress": true,
    "CvxPrismaStaking": true,
    "DataPoint": true,
    "DistributorCvxPrismaAddress": true,
    "DistributorUCrvAddress": true,
    "DistributorUCrvAddressV1": true,
    "DistributorUCrvAddressV2": true,
    "DistributorUCvxAddress": true,
    "DistributorUCvxAddressV1": true,
    "DistributorUFxsAddress": true,
    "DistributorUFxsAddressV1": true,
    "DistributorUPrismaAddress": true,
    "EffectScope": true,
    "EmptyAddress": true,
    "ExtractDefaultPropTypes": true,
    "ExtractPropTypes": true,
    "ExtractPublicPropTypes": true,
    "FxsAddress": true,
    "HistogramData": true,
    "HistogramSeriesPartialOptions": true,
    "IChartApi": true,
    "ISeriesApi": true,
    "InjectionKey": true,
    "LPxCvxFactoryAddress": true,
    "LineData": true,
    "LineSeriesPartialOptions": true,
    "LineStyle": true,
    "LineType": true,
    "MkUsdAddress": true,
    "MultisigAddress": true,
    "PirexCvxAddress": true,
    "PirexMultisigAddress": true,
    "PrismaAddress": true,
    "PrismaVotingAddress": true,
    "PropType": true,
    "PxCvxAddress": true,
    "PxCvxFactoryAddress": true,
    "Ref": true,
    "SnapshotRegistryAddress": true,
    "StkCvxPrismaAddress": true,
    "TheLlamas": true,
    "TreasuryAddress": true,
    "TreasuryArbitrumAddress": true,
    "TreasuryBaseAddress": true,
    "UBalHarvester": true,
    "UBalStrategyAddress": true,
    "UBalStrategyAddressV1": true,
    "UCrvHarvester": true,
    "UCrvHarvesterV1": true,
    "UCrvHarvesterV2": true,
    "UCrvStrategyAddress": true,
    "UCrvStrategyAddressV2": true,
    "UCvxStrategyAddress": true,
    "UFxsHarvester": true,
    "UFxsStrategyAddress": true,
    "UFxsStrategyAddressV1": true,
    "UPrismaHarvester": true,
    "UPrismaStrategyAddress": true,
    "UTCTimestamp": true,
    "UltraAddress": true,
    "UnionAddresses": true,
    "UnionBalVaultAddress": true,
    "UnionBalVaultAddressV1": true,
    "UnionCrvVaultAddress": true,
    "UnionCrvVaultAddressV1": true,
    "UnionCrvVaultAddressV2": true,
    "UnionCvxVaultAddress": true,
    "UnionFxsVaultAddress": true,
    "UnionFxsVaultAddressV1": true,
    "UnionPrismaVaultAddress": true,
    "VNode": true,
    "VlCvxAddress": true,
    "VotiumAddress": true,
    "VotiumRegistryAddress": true,
    "WEthAddress": true,
    "WritableComputedRef": true,
    "ZapsUBalAddress": true,
    "ZapsUBalAddressV1": true,
    "ZapsUBalAddressV2": true,
    "ZapsUCrv2AddressV1": true,
    "ZapsUCrvAddress": true,
    "ZapsUCrvAddressV1": true,
    "ZapsUCrvAddressV2": true,
    "ZapsUCrvAddressV3": true,
    "ZapsUCrvClaimAddress": true,
    "ZapsUCrvClaimAddressV2": true,
    "ZapsUCrvClaimAddressV3": true,
    "ZapsUCvxAddress": true,
    "ZapsUCvxAddressV1": true,
    "ZapsUCvxClaimAddress": true,
    "ZapsUCvxClaimAddressV1": true,
    "ZapsUCvxPirexClaimsAddress": true,
    "ZapsUFxsAddress": true,
    "ZapsUFxsAddressV1": true,
    "ZapsUFxsClaimAddress": true,
    "ZapsUFxsClaimAddressV1": true,
    "ZapsUPrismaAddress": true,
    "ZapsUPrismaClaimAddress": true,
    "ZapsUPrismaConvexMigrationAddress": true,
    "acceptHMRUpdate": true,
    "addDays": true,
    "asyncComputed": true,
    "autoResetRef": true,
    "bigNumToNumber": true,
    "chunk": true,
    "computed": true,
    "computedAsync": true,
    "computedEager": true,
    "computedInject": true,
    "computedWithControl": true,
    "controlledComputed": true,
    "controlledRef": true,
    "countdown": true,
    "createApp": true,
    "createEventHook": true,
    "createGlobalState": true,
    "createInjectionState": true,
    "createPinia": true,
    "createReactiveFn": true,
    "createReusableTemplate": true,
    "createSharedComposable": true,
    "createTemplatePromise": true,
    "createUnrefFn": true,
    "customRef": true,
    "debouncedRef": true,
    "debouncedWatch": true,
    "defineAsyncComponent": true,
    "defineComponent": true,
    "defineStore": true,
    "disabled": true,
    "eagerComputed": true,
    "effectScope": true,
    "extendRef": true,
    "formatNumber": true,
    "getActivePinia": true,
    "getAddress": true,
    "getAuraBalApy": true,
    "getAuraBalPrice": true,
    "getCurrentInstance": true,
    "getCurrentScope": true,
    "getCurveV2LpPrice": true,
    "getCvxApy": true,
    "getCvxCrvAprs": true,
    "getCvxCrvApy": true,
    "getCvxCrvApyV2": true,
    "getCvxCrvPrice": true,
    "getCvxCrvPriceV2": true,
    "getCvxFxsApy": true,
    "getCvxFxsLpApy": true,
    "getCvxFxsLpPrice": true,
    "getCvxFxsPrice": true,
    "getCvxPrice": true,
    "getCvxPrismaApy": true,
    "getCvxPrismaPrice": true,
    "getDefiLlamaPrice": true,
    "getPublicClient": true,
    "getPxCvxPrice": true,
    "h": true,
    "ignorableWatch": true,
    "inject": true,
    "injectLocal": true,
    "isAddress": true,
    "isDefined": true,
    "isLeaf": true,
    "isNode": true,
    "isProxy": true,
    "isReactive": true,
    "isReadonly": true,
    "isRef": true,
    "locales": true,
    "longen": true,
    "makeDestructurable": true,
    "mapActions": true,
    "mapGetters": true,
    "mapState": true,
    "mapStores": true,
    "mapWritableState": true,
    "markRaw": true,
    "minDelay": true,
    "nextTick": true,
    "notEmpty": true,
    "numToBigNumber": true,
    "onActivated": true,
    "onBeforeMount": true,
    "onBeforeRouteLeave": true,
    "onBeforeRouteUpdate": true,
    "onBeforeUnmount": true,
    "onBeforeUpdate": true,
    "onClickOutside": true,
    "onDeactivated": true,
    "onErrorCaptured": true,
    "onKeyStroke": true,
    "onLongPress": true,
    "onMounted": true,
    "onRenderTracked": true,
    "onRenderTriggered": true,
    "onScopeDispose": true,
    "onServerPrefetch": true,
    "onStartTyping": true,
    "onUnmounted": true,
    "onUpdated": true,
    "paginate": true,
    "pausableWatch": true,
    "prettyError": true,
    "provide": true,
    "provideLocal": true,
    "reactify": true,
    "reactifyObject": true,
    "reactive": true,
    "reactiveComputed": true,
    "reactiveOmit": true,
    "reactivePick": true,
    "readContract": true,
    "readonly": true,
    "ref": true,
    "refAutoReset": true,
    "refDebounced": true,
    "refDefault": true,
    "refThrottled": true,
    "refWithControl": true,
    "relativeTime": true,
    "resolveComponent": true,
    "resolveRef": true,
    "resolveUnref": true,
    "round": true,
    "roundPhil": true,
    "setActivePinia": true,
    "setMapStoreSuffix": true,
    "shallowReactive": true,
    "shallowReadonly": true,
    "shallowRef": true,
    "shorten": true,
    "simulateContract": true,
    "storeToRefs": true,
    "subIsActive": true,
    "syncRef": true,
    "syncRefs": true,
    "templateRef": true,
    "throttledRef": true,
    "throttledWatch": true,
    "toRaw": true,
    "toReactive": true,
    "toRecord": true,
    "toRef": true,
    "toRefs": true,
    "toValue": true,
    "triggerRef": true,
    "tryNotify": true,
    "tryNotifyLoading": true,
    "tryOnBeforeMount": true,
    "tryOnBeforeUnmount": true,
    "tryOnMounted": true,
    "tryOnScopeDispose": true,
    "tryOnUnmounted": true,
    "unit": true,
    "unref": true,
    "unrefElement": true,
    "until": true,
    "useActiveElement": true,
    "useAnimate": true,
    "useArrayDifference": true,
    "useArrayEvery": true,
    "useArrayFilter": true,
    "useArrayFind": true,
    "useArrayFindIndex": true,
    "useArrayFindLast": true,
    "useArrayIncludes": true,
    "useArrayJoin": true,
    "useArrayMap": true,
    "useArrayReduce": true,
    "useArraySome": true,
    "useArrayUnique": true,
    "useAsyncQueue": true,
    "useAsyncState": true,
    "useAttrs": true,
    "useBase64": true,
    "useBattery": true,
    "useBluetooth": true,
    "useBreadcrumbStore": true,
    "useBreakpoints": true,
    "useBroadcastChannel": true,
    "useBrowserLocation": true,
    "useCached": true,
    "useClipboard": true,
    "useClipboardItems": true,
    "useCloned": true,
    "useColorMode": true,
    "useConfig": true,
    "useConfirmDialog": true,
    "useCounter": true,
    "useCssModule": true,
    "useCssVar": true,
    "useCssVars": true,
    "useCurrentElement": true,
    "useCycleList": true,
    "useDark": true,
    "useDateFormat": true,
    "useDebounce": true,
    "useDebounceFn": true,
    "useDebouncedRefHistory": true,
    "useDevelopment": true,
    "useDeviceMotion": true,
    "useDeviceOrientation": true,
    "useDevicePixelRatio": true,
    "useDevicesList": true,
    "useDisplayMedia": true,
    "useDocumentVisibility": true,
    "useDraggable": true,
    "useDropZone": true,
    "useElementBounding": true,
    "useElementByPoint": true,
    "useElementHover": true,
    "useElementSize": true,
    "useElementVisibility": true,
    "useEventBus": true,
    "useEventListener": true,
    "useEventSource": true,
    "useExpansion": true,
    "useEyeDropper": true,
    "useFavicon": true,
    "useFetch": true,
    "useFileDialog": true,
    "useFileSystemAccess": true,
    "useFocus": true,
    "useFocusWithin": true,
    "useFps": true,
    "useFullscreen": true,
    "useGamepad": true,
    "useGeolocation": true,
    "useHost": true,
    "useI18n": true,
    "useIdle": true,
    "useImage": true,
    "useInfiniteScroll": true,
    "useIntersectionObserver": true,
    "useInterval": true,
    "useIntervalFn": true,
    "useKeyModifier": true,
    "useLastChanged": true,
    "useLegend": true,
    "useLightweightChart": true,
    "useLink": true,
    "useLocalStorage": true,
    "useMagicKeys": true,
    "useManualRefHistory": true,
    "useMediaControls": true,
    "useMediaQuery": true,
    "useMemoize": true,
    "useMemory": true,
    "useMounted": true,
    "useMouse": true,
    "useMouseInElement": true,
    "useMousePressed": true,
    "useMutationObserver": true,
    "useNavigatorLanguage": true,
    "useNetwork": true,
    "useNow": true,
    "useObjectUrl": true,
    "useObservable": true,
    "useOffsetPagination": true,
    "useOnline": true,
    "usePageLeave": true,
    "usePageStore": true,
    "usePagination": true,
    "usePaginationAsync": true,
    "useParallax": true,
    "useParentElement": true,
    "usePerformanceObserver": true,
    "usePermission": true,
    "usePointer": true,
    "usePointerLock": true,
    "usePointerSwipe": true,
    "usePreferredColorScheme": true,
    "usePreferredContrast": true,
    "usePreferredDark": true,
    "usePreferredLanguages": true,
    "usePreferredReducedMotion": true,
    "usePrevious": true,
    "usePromise": true,
    "useQueries": true,
    "useQuery": true,
    "useRafFn": true,
    "useReadContract": true,
    "useRefHistory": true,
    "useRelativeTime": true,
    "useResizeObserver": true,
    "useRoute": true,
    "useRouteHash": true,
    "useRouteParams": true,
    "useRouteQuery": true,
    "useRouter": true,
    "useScreenOrientation": true,
    "useScreenSafeArea": true,
    "useScriptTag": true,
    "useScroll": true,
    "useScrollLock": true,
    "useSessionStorage": true,
    "useShare": true,
    "useSlots": true,
    "useSort": true,
    "useSorted": true,
    "useSpeechRecognition": true,
    "useSpeechSynthesis": true,
    "useStepper": true,
    "useStorage": true,
    "useStorageAsync": true,
    "useStyleTag": true,
    "useSupported": true,
    "useSwipe": true,
    "useSwitchChain": true,
    "useTabNavigation": true,
    "useTemplateRefsList": true,
    "useTextDirection": true,
    "useTextSelection": true,
    "useTextareaAutosize": true,
    "useThrottle": true,
    "useThrottleFn": true,
    "useThrottledRefHistory": true,
    "useTimeAgo": true,
    "useTimeout": true,
    "useTimeoutFn": true,
    "useTimeoutPoll": true,
    "useTimestamp": true,
    "useTitle": true,
    "useToNumber": true,
    "useToString": true,
    "useToggle": true,
    "useTransition": true,
    "useUrlSearchParams": true,
    "useUserMedia": true,
    "useVModel": true,
    "useVModels": true,
    "useVibrate": true,
    "useVirtualList": true,
    "useWaitForTransactionReceipt": true,
    "useWakeLock": true,
    "useWebNotification": true,
    "useWebSocket": true,
    "useWebWorker": true,
    "useWebWorkerFn": true,
    "useWindowFocus": true,
    "useWindowScroll": true,
    "useWindowSize": true,
    "useWriteContract": true,
    "veFunderGaugeController": true,
    "veFunderGaugeFactoryAddress": true,
    "waitForTransactionReceipt": true,
    "watch": true,
    "watchArray": true,
    "watchAtMost": true,
    "watchDebounced": true,
    "watchDeep": true,
    "watchEffect": true,
    "watchIgnorable": true,
    "watchImmediate": true,
    "watchOnce": true,
    "watchPausable": true,
    "watchPostEffect": true,
    "watchSyncEffect": true,
    "watchThrottled": true,
    "watchTriggerable": true,
    "watchWithFilter": true,
    "whenever": true,
    "writeContract": true,
    "notify": true,
    "apps": true,
    "useApp": true,
    "getContract": true,
    "useExecuteContract": true,
    "useApprove": true,
    "UPxCvxAddress": true,
    "useBalance": true,
    "LPxCvxAddress": true,
    "useSocketIO": true,
    "RPxCvxAddress": true,
    "HTTPException": true,
    "Hono": true,
    "withCache": true,
    "cache": true,
    "cacheDelete": true,
    "createEnvHelpers": true,
    "useQueryClient": true,
    "useQueryRx": true,
    "isExternal": true,
    "capitalize": true,
    "uniqueId": true,
    "deepMerge": true,
    "mapKeys": true,
    "CrvUsdAddress": true,
    "useTemplateRef": true,
    "MaybeRef": true,
    "onWatcherCleanup": true,
    "useId": true,
    "useModel": true
  }
}
